bloghero/__init__.py
bloghero/cli.py
bloghero/core.py
bloghero/fonts.py
bloghero/models.py
bloghero/utils.py
bloghero-0.1.0.dist-info/LICENSE
bloghero-0.1.0.dist-info/METADATA
bloghero-0.1.0.dist-info/WHEEL
bloghero-0.1.0.dist-info/entry_points.txt
bloghero-0.1.0.dist-info/RECORD
