Metadata-Version: 2.3
Name: bloghero
Version: 0.1.0
Summary: A simple Python library and CLI tool for generating hero images by overlaying text on background images
License: MIT
Keywords: blog,hero,image,generation,cli,automation
Author: Yegor Tokmakov
Author-email: yegor@tokmakov.biz
Requires-Python: >=3.11
Classifier: Development Status :: 4 - Beta
Classifier: Intended Audience :: Developers
Classifier: License :: OSI Approved :: MIT License
Classifier: Operating System :: OS Independent
Classifier: Programming Language :: Python :: 3
Classifier: Programming Language :: Python :: 3.11
Classifier: Programming Language :: Python :: 3.12
Classifier: Topic :: Internet :: WWW/HTTP :: Dynamic Content
Classifier: Topic :: Multimedia :: Graphics
Classifier: Topic :: Software Development :: Libraries :: Python Modules
Classifier: Topic :: Text Processing :: Fonts
Provides-Extra: dev
Requires-Dist: black (>=25.1.0,<26.0.0) ; extra == "dev"
Requires-Dist: click (>=8.2.1,<9.0.0)
Requires-Dist: flake8 (>=7.3.0,<8.0.0) ; extra == "dev"
Requires-Dist: google-api-python-client (>=2.176.0,<3.0.0)
Requires-Dist: mypy (>=1.17.0,<2.0.0) ; extra == "dev"
Requires-Dist: pillow (>=11.3.0,<12.0.0)
Requires-Dist: pydantic (>=2.11.7,<3.0.0)
Requires-Dist: pytest (>=8.4.1,<9.0.0) ; extra == "dev"
Requires-Dist: pytest-cov (>=6.2.1,<7.0.0) ; extra == "dev"
Requires-Dist: requests (>=2.32.4,<3.0.0)
Project-URL: Bug Tracker, https://github.com/yegortokmakov/bloghero/issues
Project-URL: Documentation, https://github.com/yegortokmakov/bloghero#readme
Project-URL: Homepage, https://github.com/yegortokmakov/bloghero
Project-URL: Repository, https://github.com/yegortokmakov/bloghero
